AUTHORS.rst
CONTRIBUTING.rst
HISTORY.rst
LICENSE
MANIFEST.in
README.rst
setup.cfg
setup.py
docs/Makefile
docs/authors.rst
docs/conf.py
docs/contributing.rst
docs/history.rst
docs/index.rst
docs/installation.rst
docs/make.bat
docs/readme.rst
docs/usage.rst
pictosquare/__init__.py
pictosquare/colorthief.py
pictosquare/folderfetcher.py
pictosquare/imagesquarer.py
pictosquare/pictosquare.py
pictosquare.egg-info/PKG-INFO
pictosquare.egg-info/SOURCES.txt
pictosquare.egg-info/dependency_links.txt
pictosquare.egg-info/entry_points.txt
pictosquare.egg-info/not-zip-safe
pictosquare.egg-info/requires.txt
pictosquare.egg-info/top_level.txt
tests/__init__.py
tests/test_pictosquare.py