Metadata-Version: 1.2
Name: pictosquare
Version: 0.1.1
Summary: picToSquare (Pic To Square) is an experimental python script that 'squares up' every picture in a directory  to be Instagram ready.
Home-page: https://github.com/hithismani/pictosquare
Author: Mani Kumar
Author-email: hi@manikumar.in
License: MIT license
Keywords: pictosquare
Platform: UNKNOWN
Classifier: Development Status :: 2 - Pre-Alpha
Classifier: Intended Audience :: Developers
Classifier: License :: OSI Approved :: MIT License
Classifier: Natural Language :: English
Classifier: Programming Language :: Python
Classifier: Programming Language :: Python :: 2.7
Classifier: Programming Language :: Python :: 3
Classifier: Programming Language :: Python :: 3.5
Classifier: Programming Language :: Python :: 3.6
Classifier: Programming Language :: Python :: 3.7
Classifier: Programming Language :: Python :: 3.8
Requires-Python: >=2.7, !=3.0.*, !=3.1.*, !=3.2.*, !=3.3.*, !=3.4.*
